dvc_http/__init__.py
dvc_http/_dvc_http_version.py
dvc_http/retry.py
dvc_http/spec.py
dvc_http/tests/__init__.py
dvc_http/tests/cloud.py
dvc_http/tests/conftest.py
dvc_http/tests/fixtures.py
dvc_http/tests/httpd.py
dvc_http/tests/test_config.py
dvc_http/tests/test_dvc.py
dvc_http-2.32.0.dist-info/LICENSE
dvc_http-2.32.0.dist-info/METADATA
dvc_http-2.32.0.dist-info/WHEEL
dvc_http-2.32.0.dist-info/top_level.txt
dvc_http-2.32.0.dist-info/RECORD
